{
  "entry_id": "n5_011_ga",
  "card_blurb": "「が」像句子里的聚光灯：把“谁/什么正在做、正在发生”一下照亮；放在句中时，又常轻轻带出一个“不过……”。",
  "feel": "这句听起来像：在人群里手一指，说“就是他”“就是这个在发生”。不是铺陈背景，而是把主语猛地推到前面。",
  "family_position": "它在本家族里站哪一格：在「は」把话题摆上桌之后，「が」负责把真正的主语点亮。它和「は」最容易混，但功能不同；再往旁边看，「も」「だけ」常常就在同一个名词位上，把“点名”改成“也”或“只有”。",
  "scene_paragraph": "教室里老师问：“だれがピアノを弾けますか。” 大家都在看别人，后排一个同学小声说：“田[た]中[なか]さんが弾[ひ]けます。” 这一句的重点不是介绍田中这个人，而是从一群人里把“会弹的那个人”挑出来。`が` 就像镜头突然对焦：谁来了，哪里下雨了，外面什么在响，哪家店便宜但是远，日语里这种“现在就是它”的感觉，最常轮到「が」出场。",
  "scene_examples": [
    {
      "tag": "点名回答",
      "jp_ruby": "だれが鍵[かぎ]を持[も]っていますか。山[やま]田[だ]さんが持[も]っています。",
      "zh": "谁拿着钥匙？山田拿着。",
      "note": "回答“谁”时，`が` 直接把答案锁定出来。"
    },
    {
      "tag": "眼前变化",
      "jp_ruby": "雨[あめ]が降[ふ]ってきました。洗[せん]濯[たく]物[もの]、入[い]れましょう。",
      "zh": "下起雨来了。把衣服收进来吧。",
      "note": "天气、声音、出现变化时，`が` 很常把当前发生的事推到前景。"
    },
    {
      "tag": "轻微转折",
      "jp_ruby": "この店[みせ]、安[やす]いですが、少[すこ]し遠[とお]いです。",
      "zh": "这家店很便宜，不过有点远。",
      "note": "句中 `が` 常带轻轻一转的“不过……”，语气比硬转折柔和。"
    }
  ],
  "formula": "N が + 述语；句子 + が、后句",
  "formula_explainer": "最核心的是“名词 + が + 述语”，用来锁定主语：谁做、什么在发生、哪一个成立。另一个高频支线是把「が」放在前后两句中间，前句先说成立，后句再补一个“不过……”。",
  "structure_cards": [
    {
      "label": "回答谁",
      "note": "问句里要把主语点出来时最常见。",
      "jp_ruby": "だれがこの写[しゃ]真[しん]を撮[と]りましたか。父[ちち]が撮[と]りました。",
      "zh": "这张照片是谁拍的？我爸爸拍的。",
      "mini_note": "候选人里，真正那个被 `が` 打亮。"
    },
    {
      "label": "出现了什么",
      "note": "声音、天气、存在、变化这类句子很爱用。",
      "jp_ruby": "外[そと]で変[へん]な音[おと]がしています。",
      "zh": "外面传来奇怪的声音。",
      "mini_note": "不是聊“声音”这个话题，而是说“有个声音正在出现”。"
    },
    {
      "label": "前半成立，不过……",
      "note": "礼貌说明后，再接保留意见或反面信息。",
      "jp_ruby": "日[に]本[ほん]語[ご]は少[すこ]し分[わ]かりますが、まだ話[はな]せません。",
      "zh": "日语我懂一点，不过还不会说。",
      "mini_note": "这里的 `が` 更像中文里的“不过”。"
    }
  ],
  "usage_points": [
    "一旦前面是 `だれが / 何が / どれが` 这类问句，答案里很容易就是 `が`，因为你是在锁定答案。",
    "天气、声音、有人来了、东西出现了这类“眼前冒出来的情况”，日语很爱用 `が` 把它推到前景。",
    "在 `好きです`、`分かります`、`あります / います` 这类句子里，前面的对象也常用 `が`，因为这里更像“某对象处在这个状态里”，不是普通宾语思路。",
    "`は` 和 `が` 都可能被中文直觉翻成“是/会”，但 `は` 像“说到……”，`が` 像“就是……”。做题时先判断你是在换话题，还是在点名。",
    "放在两句中间的 `が` 多半不是主语助词，而是轻转折。`ですが` 比 `でも` 更柔和，也更像口语和礼貌表达里的常客。",
    "同一个名词位如果换成 `も`、`だけ`，意思会立刻变成“也”“只有”。所以看到这些词时，要意识到它们常常把原本的 `が` 顶掉。"
  ],
  "contrasts": [
    {
      "other_entry_id": "n5_079_wa_topic_marker",
      "title": "が vs は",
      "self_label": "回答“谁去”时点名主语",
      "other_label": "把“我”当作话题来说明",
      "difference": "`が` 像聚光灯，专门锁定“到底是谁”；`は` 像把一个人摆上桌，再对他做评论。中文都可能看成“我去”，但语感完全不同。",
      "example_self": {
        "jp_ruby": "だれが行[い]きますか。私[わたし]が行[い]きます。",
        "zh": "谁去？我去。",
        "note": "这是在回答“谁”。"
      },
      "example_other": {
        "jp_ruby": "私[わたし]は行[い]きます。",
        "zh": "至于我，我会去。",
        "note": "这是把“我”当话题来陈述。"
      },
      "exam_handle": "看到前面有 `だれ`、后面是在回答谁做某事，空格优先想 `が`；如果名词已经是全句的话题，后面只是补充说明，就更像 `は`。"
    },
    {
      "other_entry_id": "n5_060_o_wo",
      "title": "が vs を",
      "self_label": "が = 做动作的人",
      "other_label": "を = 动作碰到的对象",
      "difference": "`が` 标出动作或状态的发出者，`を` 标出动作直接碰到的对象。两者常在同一句里一起出现，但站位完全不同。",
      "example_self": {
        "jp_ruby": "犬[いぬ]が男[おとこ]の子[こ]を追[お]いかけています。",
        "zh": "狗在追男孩。",
        "note": "狗是动作发出者，所以用 `が`。"
      },
      "example_other": {
        "jp_ruby": "男[おとこ]の子[こ]が犬[いぬ]を追[お]いかけています。",
        "zh": "男孩在追狗。",
        "note": "狗变成被追的对象，所以用 `を`。"
      },
      "exam_handle": "先找动词是谁发出的，那个位置更可能是 `が`；被动作影响、被追、被看、被吃的对象，才是 `を`。"
    },
    {
      "other_entry_id": "n5_034_mo",
      "title": "が vs も",
      "self_label": "只是点出主语",
      "other_label": "在已有名单上再加一个“也”",
      "difference": "`が` 只是说明“是谁”；`も` 会把前文已有的人或事一起拉进来，带出“他也一样”的附加感。",
      "example_self": {
        "jp_ruby": "明[あ]日[した]は山[やま]田[だ]さんが来[き]ます。",
        "zh": "明天山田会来。",
        "note": "只是点出谁会来。"
      },
      "example_other": {
        "jp_ruby": "明[あ]日[した]は山[やま]田[だ]さんも来[き]ます。",
        "zh": "明天山田也会来。",
        "note": "前面通常已有别人会来，山田被加进名单。"
      },
      "exam_handle": "如果语境里已经有人做同样的事，空格优先想 `も`；如果只是说明到底是谁，还是回到 `が` 的“点名”感觉。"
    }
  ],
  "memory_chain": "记这组家族时，可以顺着一条线走：先用「は」把话题摆上桌，再用「が」把真正站在聚光灯下的主语挑出来；动作碰到谁，用「を」；是谁的、什么的，用「の」；同样也算上一个，用「も」；最后如果只剩一个，就换成「だけ」。所以「が」不是孤零零的一粒助词，它正站在整条句子骨架里“点主语”的那一格。"
}