{
  "entry_id": "n5_084_yori_hou_ga",
  "card_blurb": "先拿 A 当参照，再说 B 这一边更……。这是日语里非常常用的“两样一比，偏向后者”的句型。",
  "feel": "这句听起来像把两样东西摆在桌上，先瞄一眼 A，再把手指向 B 说：“跟那个比，还是这个更……”；有很强的日常选择感、偏好感。",
  "family_position": "它站在这条“比较・程度尺子”里最核心的“比较格”。前面的「とても」「すぎる」还只是看程度高不高、有没有过线；到「より〜ほうが」这里，才真正把两边放上同一把尺。再往后，就会升级成「一番」「の中で[A]が一番」这种排行表达。",
  "scene_paragraph": "午休时你站在便利店冰柜前，左边是咖啡，右边是茶，同事问你下午开会前想喝什么。你想了一秒，说“比起咖啡，还是茶更合适”。这种时候，你不是在背抽象的“比较级”，而是在眼前两个选项里，顺手把更适合、更喜欢、更方便的那一个推出来。「より〜ほうが」最像这样的场景：点餐、选路、聊喜好、做小判断。",
  "scene_examples": [
    {
      "tag": "便利店",
      "jp_ruby": "朝[あさ]はコーヒーよりお茶[ちゃ]のほうが飲[の]みやすいです。",
      "zh": "早上比起咖啡，茶更容易喝下去。",
      "note": "说的是当下更适合自己的选择。"
    },
    {
      "tag": "上学路",
      "jp_ruby": "この時間[じかん]はバスより自転車[じてんしゃ]のほうが早[はや]いよ。",
      "zh": "这个时间比起公交，自行车更快哦。",
      "note": "聊天里很常这样做现实判断。"
    },
    {
      "tag": "备考",
      "jp_ruby": "図書館[としょかん]より家[いえ]のほうが静[しず]かで集中[しゅうちゅう]できます。",
      "zh": "比起图书馆，家里更安静，更能集中。",
      "note": "后面常顺着补出“为什么更好”。"
    }
  ],
  "formula": "Aより Bのほうが + 形容词 / 好きです / いいです / 便利です",
  "formula_explainer": "`Aより` 是拿来比较的基准，`Bのほうが` 是“B 这一边更……”。它不只是客观比较，也很常拿来表达个人偏好、哪种做法更合适、哪边更方便。",
  "structure_cards": [
    {
      "label": "基础比较",
      "note": "先说参照物，再给出更强的一边。",
      "jp_ruby": "スーパーより駅前[えきまえ]の店[みせ]のほうが安[やす]いです。",
      "zh": "比起超市，车站前的店更便宜。",
      "mini_note": "最标准骨架：AよりBのほうがAdjです。"
    },
    {
      "label": "主观喜好",
      "note": "和「好き」「いい」搭配特别自然。",
      "jp_ruby": "パンよりご飯[はん]のほうが好[す]きです。",
      "zh": "比起面包，我更喜欢米饭。",
      "mini_note": "不只是客观事实，也常说个人口味。"
    },
    {
      "label": "方案对比",
      "note": "前项也可以是动作或做法。",
      "jp_ruby": "雨[あめ]の日[ひ]は歩[ある]くよりタクシーのほうが楽[らく]です。",
      "zh": "下雨天比起走路，还是坐出租更轻松。",
      "mini_note": "比较的不一定只是两个名词，也可以是两个选择。"
    }
  ],
  "usage_points": [
    "`Aより` 不是赢家，它只是“拿来比的那一边”；真正被推出来的是 `Bのほうが`。",
    "`ほう` 的感觉像“这一边、这一方”，所以整句不像数学公式，更像把两边摆出来后说“还是 B 这边更……”。",
    "这条特别适合口语里的偏好和选择：吃哪个、坐什么、哪边更方便、哪个更快。",
    "它和「は〜より・・・です」意思很接近，但镜头不一样：这条先说基准，后者先说主角。",
    "如果题目是在一组里挑“最……”，就不要停在这条，往往要换成「一番」或「の中で[A]が一番」。"
  ],
  "contrasts": [
    {
      "other_entry_id": "n5_080_wa_yori_desu",
      "title": "より～ほうが vs は〜より・・・です",
      "self_label": "先说基准，再说更强的一边",
      "other_label": "先说主角，再说它比谁更……",
      "difference": "两句核心意思几乎一样，差别主要在镜头。`より〜ほうが` 像“跟 A 比的话，B 更……”；`は〜より・・・です` 则是先把 B 立成话题，再补比较对象。",
      "example_self": {
        "jp_ruby": "バスより地下鉄[ちかてつ]のほうが速[はや]いです。",
        "zh": "比起公交，地铁更快。",
        "note": "先摆出参照物 `バス`。"
      },
      "example_other": {
        "jp_ruby": "地下鉄[ちかてつ]はバスより速[はや]いです。",
        "zh": "地铁比公交更快。",
        "note": "先把 `地下鉄` 当成话题来说。"
      },
      "exam_handle": "如果空格附近同时出现 `より` 和 `ほうが`，大概率就是这条；如果句子一上来是 `Bは`，再接 `Aより`，更像「は〜より・・・です」。"
    },
    {
      "other_entry_id": "n5_017_ichiban",
      "title": "より～ほうが vs 一番",
      "self_label": "两样里更喜欢后者",
      "other_label": "一组里最喜欢它",
      "difference": "`より〜ほうが` 是把 A 和 B 放在一起比，结论是“B 比 A 更……”；`一番` 直接站到最高点，说“最……”，不一定把比较对象逐个说出来。",
      "example_self": {
        "jp_ruby": "りんごよりみかんのほうが好[す]きです。",
        "zh": "比起苹果，我更喜欢橘子。",
        "note": "这是两样之间的偏好比较。"
      },
      "example_other": {
        "jp_ruby": "果物[くだもの]はみかんが一番[いちばん]好[す]きです。",
        "zh": "水果里我最喜欢橘子。",
        "note": "这里已经不是二选一，而是在一类里说“最喜欢”。"
      },
      "exam_handle": "题目里若有明确比较基准 `Aより`，先想这条；如果是在说“最……”、没有把基准逐个摆出来，就更可能是「一番」。"
    },
    {
      "other_entry_id": "n5_057_no_naka_de_a_ga_ichiban",
      "title": "より～ほうが vs の中で[A]が一番",
      "self_label": "先拿两家店对比",
      "other_label": "在整组里排第一",
      "difference": "前者只是局部比较，意思是“B 比 A 更……”；后者带 `の中で`，明确告诉你是在某个范围里排第一。",
      "example_self": {
        "jp_ruby": "駅前[えきまえ]の店[みせ]より公園前[こうえんまえ]の店[みせ]のほうが静[しず]かです。",
        "zh": "比起车站前那家店，公园前那家更安静。",
        "note": "这里只是在比两家。"
      },
      "example_other": {
        "jp_ruby": "この三[みっ]つの店[みせ]の中[なか]で、公園前[こうえんまえ]の店[みせ]が一番[いちばん]静[しず]かです。",
        "zh": "这三家店里，公园前那家最安静。",
        "note": "范围一出来，就变成组内排行了。"
      },
      "exam_handle": "看到 `の中で` 就先想到“范围 + 第一名”；只有 `より〜ほうが`，只是两边放到尺子上比一比，不等于全场第一。"
    }
  ],
  "memory_chain": "记这条时，把整条家族线一起带上：先有「とても」把程度拉高，再有「すぎる」告诉你高到过线；接着到了「より〜ほうが」，开始把两样东西摆上尺子比较。换个镜头，就是「は〜より・・・です」。如果不只比两样，而是要从一组里挑最强，就继续走到「一番」和「の中で[A]が一番」。整条记忆链可以压成一句：很 -> 太 -> 更 -> 最。"
}