{
  "entry_id": "n4_093_te_hoshii",
  "card_blurb": "在这组“帮忙系”里，`てほしい`不是描述谁已经帮了谁，而是把镜头停在前一秒：我希望你来做。",
  "feel": "听起来像把自己的期待直接放到对方动作上：不是硬邦邦下命令，但也不是纯客观描述，里面有一种“这件事我希望你这样处理”的心情。",
  "family_position": "它站在本家族的“愿望位”。`てあげる`是我给别人做，`てくれる`是别人为我做，`てもらう`是我得到别人帮忙；到了`てほしい`，动作还没发生，我只是先说“希望你去做”。",
  "scene_paragraph": "想象一下合租生活。你不是第一次提醒室友了，他还是常常很晚回家也不先说一声，害你一直担心。你这次说的不是单纯抱怨，也不是记叙事实，而是把心里的期待直接讲出来：`遅くなるなら、先に連絡してほしい。` 这就是`てほしい`最典型的场景。事情还没发生，但你已经把“我希望你这样做”的方向指给对方了。",
  "scene_examples": [
    {
      "tag": "改稿现场",
      "jp_ruby": "この段落[だんらく]、もう少[すこ]し短[みじか]くしてほしい。",
      "zh": "这一段我想让你再压短一点。",
      "note": "工作里很常见，用来提修改期待，比直接命令软一些。"
    },
    {
      "tag": "合租规则",
      "jp_ruby": "夜[よる]、帰[かえ]るのが遅[おそ]いなら、先[さき]にメッセージしてほしい。",
      "zh": "如果晚上会晚回来，希望你先发个消息。",
      "note": "不是一次性帮忙，而是对对方行为方式的期待。"
    },
    {
      "tag": "别这样做",
      "jp_ruby": "大事[だいじ]なことは、一人[ひとり]で決[き]めないでほしい。",
      "zh": "重要的事，我希望你不要一个人决定。",
      "note": "`ないでほしい`是生活会话里特别高频的变体。"
    }
  ],
  "formula": "人に Vてほしい / 人に Vないでほしい",
  "formula_explainer": "前面放“谁去做”，后面放你希望发生的动作。直接对对方说时，执行者常常省略；如果是不希望对方那样做，就改成`ないでほしい`。",
  "structure_cards": [
    {
      "label": "点出执行者",
      "note": "把“谁来做”说清楚",
      "jp_ruby": "田中[たなか]さんにこの部分[ぶぶん]を確認[かくにん]してほしい。",
      "zh": "我想让田中先生确认一下这一部分。",
      "mini_note": "`に`标出的是动作执行者。"
    },
    {
      "label": "对话里省略人",
      "note": "眼前是谁很清楚时，人可以不说",
      "jp_ruby": "もう少[すこ]しゆっくり話[はな]してほしい。",
      "zh": "我希望你说得再慢一点。",
      "mini_note": "默认就是在对面前的人提期待。"
    },
    {
      "label": "否定愿望",
      "note": "表达“不希望你这样做”",
      "jp_ruby": "その話[はなし]、まだみんなに言[い]わないでほしい。",
      "zh": "那件事，我希望你先别跟大家说。",
      "mini_note": "比生硬禁止更像带着顾虑地请求。"
    }
  ],
  "usage_points": [
    "`てほしい`的重点是“我希望你做”，不是“你已经帮了我”。动作通常还在未来，核心是期待感。",
    "动作执行者常用`に`标出，如`先生[せんせい]に見[み]てほしい`；但在面对面说话时，对方很明确，常常直接省略。",
    "它比命令柔和，但不自动等于礼貌。对上司、客户直接说`〜てほしい`可能还是偏直，正式场合常换更缓的说法。",
    "`ないでほしい`非常常见，尤其适合表达“不希望你这样做”，语气通常比禁止句更有人情味。",
    "如果要说“别人希望谁做”，常接`と思[おも]っている`、`言[い]っていた`等，如`母[はは]は私[わたし]に早[はや]く帰[かえ]ってほしいと言[い]っていた`。",
    "和家族里的`てくれる`、`てもらう`分清：`てほしい`是愿望还在前面，后两者更像帮忙已经落实，或至少站在“得到帮助”的角度说。"
  ],
  "contrasts": [
    {
      "other_entry_id": "n4_097_te_kureru",
      "title": "てほしい vs てくれる",
      "self_label": "我希望你关窗",
      "other_label": "你帮我关窗",
      "difference": "`てほしい`是事情发生前的期待；`てくれる`是站在“对方为我做了”这个受益视角回看动作。",
      "example_self": {
        "jp_ruby": "寒[さむ]いから、窓[まど]を閉[し]めてほしい。",
        "zh": "有点冷，我想让你把窗户关上。",
        "note": "动作还没发生，我在提出希望。"
      },
      "example_other": {
        "jp_ruby": "寒[さむ]かったから、窓[まど]を閉[し]めてくれた。",
        "zh": "刚才有点冷，你帮我把窗户关上了。",
        "note": "动作已经发生，我在说对方为我做了。"
      },
      "exam_handle": "空格如果落在“希望、拜托、最好你来做”的位置，优先想`てほしい`；如果后文带感谢、结果、受惠感，通常更像`てくれる`。"
    },
    {
      "other_entry_id": "n4_100_te_morau",
      "title": "てほしい vs てもらう",
      "self_label": "我希望老师看报告",
      "other_label": "我请老师看了报告",
      "difference": "`てほしい`只把愿望说出来；`てもらう`强调我已经把这份帮助拿到手，常带“去请求并得到结果”的感觉。",
      "example_self": {
        "jp_ruby": "先生[せんせい]にレポートを見[み]てほしい。",
        "zh": "我想让老师看一下报告。",
        "note": "还停在期待阶段。"
      },
      "example_other": {
        "jp_ruby": "先生[せんせい]にレポートを見[み]てもらった。",
        "zh": "我请老师看了报告。",
        "note": "已经实际得到老师的帮助了。"
      },
      "exam_handle": "如果句子重点是“想让某人做”，选`てほしい`；如果重点是“我让某人做了，并且这件事成了”，尤其有结果感或过去式，选`てもらう`。"
    },
    {
      "other_entry_id": "n4_092_te_ageru",
      "title": "てほしい vs てあげる",
      "self_label": "我想让弟弟送奶奶去车站",
      "other_label": "弟弟送奶奶去车站",
      "difference": "`てほしい`是我把期待放到别人身上；`てあげる`是某人主动为别人做。一个在说“希望谁做”，一个在说“谁替谁做”。",
      "example_self": {
        "jp_ruby": "弟[おとうと]におばあちゃんを駅[えき]まで送[おく]ってほしい。",
        "zh": "我想让弟弟送奶奶去车站。",
        "note": "我在安排或期待弟弟去做。"
      },
      "example_other": {
        "jp_ruby": "弟[おとうと]はおばあちゃんを駅[えき]まで送[おく]ってあげた。",
        "zh": "弟弟送奶奶去车站了。",
        "note": "动作已经由弟弟做出来，而且是“为奶奶做”。"
      },
      "exam_handle": "看到说话人是在表达期待、请求别人行动，用`てほしい`；如果主语自己或某人已经对受益者施了帮助，用`てあげる`。"
    }
  ],
  "memory_chain": "这组家族最好按镜头顺着记：`てあげる`/`てやる`是我把动作给出去，`てくれる`是动作朝我过来，`てもらう`是我把这份帮忙领到手；而`てほしい`站在动作发生之前，先把“希望你这么做”的期待抛出去。记成“给出去 → 朝我来 → 我收到 → 我希望你做”，这条链就不容易乱。"
}