{
  "entry_id": "n4_110_to_iu",
  "card_blurb": "把前面的词或整句话先贴上“就这么叫 / 就这么说”的标签，再把它接到后面去。",
  "feel": "这句听起来像在说：“前面那一段，我先把它当成一个名字、一个说法、一个内容块，再拿出来介绍。” 它不是急着表态，而是先把内容装箱、挂牌。",
  "family_position": "它站在“引用・说法出口系”的起点格：先负责把前面的词或句子变成“被这样叫、被这样说”的东西。后面的「って」是它的聊天口语版，「と思う」是在这个出口后再加上“我的判断”，“かどうか”则是把内容装进“是否”的盒子里；再往前一步缓和评价，就是「と言ってもいい」。",
  "scene_paragraph": "会议室里，新同事指着投影上的外来词发问：“这个到底什么意思？” 旁边的人往往不会只丢一个词典释义，而是会先把那个词拎出来，当成一个“被这么叫的东西”来解释。又或者群里有人转消息，说下周楼下要开新店，大家传来传去时，其实也是把整句话打包成一个“消息”“传闻”。「という」就是这个打包动作：先命名、先挂牌，再往后解释、介绍、转述。",
  "scene_examples": [
    {
      "tag": "约见地点",
      "jp_ruby": "駅[えき]の近[ちか]くに「青[あお]い扉[とびら]」というカフェがあるから、そこで待[ま]ち合[あ]わせよう。",
      "zh": "车站附近有一家叫“蓝色之门”的咖啡馆，我们就在那儿碰头吧。",
      "note": "先报名字，再说它是什么。"
    },
    {
      "tag": "课堂笔记",
      "jp_ruby": "先生[せんせい]は「無理[むり]をしない」という考[かんが]え方[かた]も大事[だいじ]だと言[い]っていた。",
      "zh": "老师说，“不要硬撑”这种想法也很重要。",
      "note": "前面放整句话，后面接名词来解释。"
    },
    {
      "tag": "群聊传闻",
      "jp_ruby": "来週[らいしゅう]からこのビルの一階[いっかい]にパン屋[や]ができるといううわさ、もう聞[き]いた？",
      "zh": "你已经听说“下周起这栋楼一层会开面包店”这个传闻了吗？",
      "note": "整条消息被打包成“传闻”。"
    }
  ],
  "formula": "「名称・词语」+ という + 名詞 / 普通形 + という + 名詞",
  "formula_explainer": "前面放名字或词语时，常是“叫作……的……”；前面放一整句话时，就是把整句话压成一个内容块，再接“消息、传闻、想法、词语”之类的名词。",
  "structure_cards": [
    {
      "label": "给东西挂名字",
      "note": "「名称」という + 名詞",
      "jp_ruby": "「北[きた]の窓[まど]」という雑貨店[ざっかてん]で、母[はは]の誕生日[たんじょうび]プレゼントを買[か]った。",
      "zh": "我在一家叫“北窗”的杂货店买了妈妈的生日礼物。",
      "mini_note": "后面的名词才是本体，前面的只是名字。"
    },
    {
      "label": "把词拿出来解释",
      "note": "「词语」という + 言葉・考え方 など",
      "jp_ruby": "「普通[ふつう]」という言葉[ことば]ほど、人[ひと]によって基準[きじゅん]が違[ちが]う。",
      "zh": "像“普通”这种词，不同的人标准都不一样。",
      "mini_note": "很常见于解释词语、概念、标题。"
    },
    {
      "label": "把整句装进名词前",
      "note": "普通形 + という + 名詞",
      "jp_ruby": "今夜[こんや]は雨[あめ]になるという天気予報[てんきよほう]を見[み]て、傘[かさ]を持[も]って出[で]た。",
      "zh": "看到“今晚会下雨”的天气预报后，我带着伞出门了。",
      "mini_note": "像把一句话装进“预报、消息、传闻”这些盒子里。"
    }
  ],
  "usage_points": [
    "`AというB` 里真正要介绍的是 `B`，`A` 是名字或标签，所以常译成“叫A的B / 所谓A的B”。",
    "前面不只可以放名字，也常放一个词或概念，用来引出“这个词/这个说法/这种想法”。",
    "前面如果是一整句话，后面通常要接一个承接名词，比如“消息、传闻、通知、想法”；它的感觉不是句子结束了，而是句子被打包后继续往下接。",
    "`という` 带一点中性、说明感；口语里常松成 `って`，但标准叙述、书面表达、考试空格里更常见的是 `という`。",
    "如果句子的重点是“我觉得……”，先想到的是 `と思う`；`という` 更像把内容递出去，本身不替你表态。",
    "看到 `〜といいます`（我叫……）时也可以顺手连起来记：都是把“名称/说法”接出来，只是本条更常见于修饰后面的名词。"
  ],
  "contrasts": [
    {
      "other_entry_id": "n4_118_tte",
      "title": "という vs って",
      "self_label": "标准说明型",
      "other_label": "口语点名型",
      "difference": "`という` 比较中性、稳，像在认真介绍一个名字或说法；`って` 是聊天里顺手扔出来的口语版，更轻，也更像“你知道那个……”的语气。",
      "example_self": {
        "jp_ruby": "この近[ちか]くに「雨音[あまおと]」という本屋[ほんや]がある。",
        "zh": "这附近有一家叫“雨声”的书店。",
        "note": "中性说明，像在认真介绍。"
      },
      "example_other": {
        "jp_ruby": "この近[ちか]くに「雨音[あまおと]」って本屋[ほんや]がある。",
        "zh": "这附近有一家叫“雨声”的书店。",
        "note": "口语更随手，像聊天里顺口提名字。"
      },
      "exam_handle": "看到空格后面接名词、整句语气偏标准说明时，先想 `という`；如果整句像朋友聊天、转述口气很轻，再考虑 `って`。"
    },
    {
      "other_entry_id": "n4_114_to_omou",
      "title": "という vs と思う",
      "self_label": "内容打包型",
      "other_label": "主观判断型",
      "difference": "`という` 是把前面的内容包装成一个可被转述的“信息块”；`と思う` 是说话人把自己的判断贴上去。一个在传内容，一个在表意见。",
      "example_self": {
        "jp_ruby": "田中[たなか]さんは今月[こんげつ]で辞[や]めるという話[はなし]を聞[き]いた。",
        "zh": "我听说了“田中这个月要离职”的消息。",
        "note": "重点是那条消息本身。"
      },
      "example_other": {
        "jp_ruby": "田中[たなか]さんは今月[こんげつ]で辞[や]めると思[おも]う。",
        "zh": "我觉得田中这个月会离职。",
        "note": "重点是我的判断。"
      },
      "exam_handle": "空格后面如果还有“消息、传闻、通知”之类的名词，优先想 `という`；如果句子要落在“我觉得”上，优先想 `と思う`。"
    },
    {
      "other_entry_id": "n4_026_ka_dou_ka",
      "title": "という vs かどうか",
      "self_label": "内容转述型",
      "other_label": "是否判断型",
      "difference": "`という` 说的是“有这样一条内容”；`かどうか` 说的是“这件事成立不成立”。前者把信息往外送，后者把信息装进“是否”的判断里。",
      "example_self": {
        "jp_ruby": "社長[しゃちょう]が来[く]るという連絡[れんらく]が先[さき]に来[き]た。",
        "zh": "先收到了“社长会来”的通知。",
        "note": "内容被当成已转来的信息。"
      },
      "example_other": {
        "jp_ruby": "社長[しゃちょう]が来[く]るかどうか、まだ分[わ]からない。",
        "zh": "社长来不来，现在还不知道。",
        "note": "焦点是“是否会来”。"
      },
      "exam_handle": "如果空格处要表达“是否”，或后面常接“知道、确认、问”等判断类动词，优先想 `かどうか`；如果后面是“通知、消息、传闻”，优先想 `という`。"
    }
  ],
  "memory_chain": "记这组时可以走一条线：先用「という」把词或句子挂牌，变成“被这样说的内容块”；到了聊天里，它常松成「って」；如果你要继续说“我是这么想的”，就接到「と思う」；如果你想把说法放软成“这么讲也行”，走到「と言ってもいい」；如果重点不在内容本身，而在“是不是这样”，就转去「かどうか」。先认出出口，再看这个出口后面接的是名字、判断、缓和评价，还是是否问题。"
}